pyproxmox3/__init__.py
pyproxmox3-1.0.3.dist-info/LICENSE
pyproxmox3-1.0.3.dist-info/METADATA
pyproxmox3-1.0.3.dist-info/WHEEL
pyproxmox3-1.0.3.dist-info/top_level.txt
pyproxmox3-1.0.3.dist-info/RECORD
